label_convert/__init__.py
label_convert/coco_to_labelImg.py
label_convert/darknet_to_coco.py
label_convert/labelImg_to_publaynet.py
label_convert/labelImg_to_yolov5.py
label_convert/labelme_to_coco.py
label_convert/vis_coco.py
label_convert/yolov5_to_coco.py
label_convert/yolov5_to_yolov8.py
label_convert/yolov5_yaml_to_coco.py
label_convert/yolov8_to_yolov5.py
label_convert-0.2.0.dist-info/LICENSE
label_convert-0.2.0.dist-info/METADATA
label_convert-0.2.0.dist-info/WHEEL
label_convert-0.2.0.dist-info/entry_points.txt
label_convert-0.2.0.dist-info/top_level.txt
label_convert-0.2.0.dist-info/RECORD
